{"gtabs":[{"panes":[{"ptabs":[{"history":[{"dir":"/home/hamid","file":"..","relpos":0,"ts":1615983484},{"dir":"/home","file":"hamid","relpos":1,"ts":1615983484},{"dir":"/","file":"etc","relpos":4,"ts":1615993382},{"dir":"/home/hamid","file":"Downloads","relpos":1,"ts":1616069134},{"dir":"/home/hamid/Downloads","file":"Telegram Desktop","relpos":1,"ts":1616069134},{"dir":"/home/hamid/Downloads/Telegram Desktop","file":"Screenshot from 2021-03-18 15-28-40.png","relpos":1,"ts":1616069134},{"dir":"/home/hamid","file":"Downloads","relpos":1,"ts":1616078371},{"dir":"/home","file":"hamid","relpos":1,"ts":1616078371}],"filters":{"invert":true,"dot":true,"manual":"","auto":""},"last-location":"/home","sorting":[2],"preview":false}]},{"ptabs":[{"history":[{"dir":"/home/hamid","file":"..","relpos":0,"ts":1615983484}],"filters":{"invert":true,"dot":true,"manual":"","auto":""},"last-location":"/home/hamid","sorting":[2],"preview":false}]}],"active-pane":0,"preview":false,"splitter":{"pos":-1,"ratio":0.5,"orientation":"v","expanded":true}}],"trash":[{"trashed":"/home/hamid//.local/share/vifm/Trash/000_config","original":"/home/hamid/Downloads/Telegram Desktop/config"},{"trashed":"/home/hamid//.local/share/vifm/Trash/000_id_rsa","original":"/home/hamid/Downloads/Telegram Desktop/id_rsa"},{"trashed":"/home/hamid//.local/share/vifm/Trash/000_id_rsa.pub","original":"/home/hamid/Downloads/Telegram Desktop/id_rsa.pub"},{"trashed":"/home/hamid//.local/share/vifm/Trash/000_kaveh-phone.ovpn","original":"/home/hamid/Downloads/Telegram Desktop/kaveh-phone.ovpn"},{"trashed":"/home/hamid//.local/share/vifm/Trash/000_ticket_1023753546.pdf","original":"/home/hamid/Downloads/Telegram Desktop/ticket_1023753546.pdf"}],"marks":{"H":{"dir":"/home/hamid//","file":"..","ts":1615983482},"b":{"dir":"/home/hamid//bin/","file":"..","ts":1615983482},"h":{"dir":"/home/hamid//","file":"..","ts":1615983482},"z":{"dir":"/home/hamid//.config/vifm","file":"..","ts":1615983482}},"bmarks":{},"cmd-hist":[{"text":"only","ts":1615993382},{"text":"!wev %c","ts":1616078365}],"regs":{"\"":["/home/hamid//.local/share/vifm/Trash/000_kaveh-phone.ovpn"]},"dir-stack":[],"use-term-multiplexer":false}